upversion/__init__.py
upversion/upversion.py
incver-0.0.1.dist-info/LICENSE
incver-0.0.1.dist-info/METADATA
incver-0.0.1.dist-info/WHEEL
incver-0.0.1.dist-info/entry_points.txt
incver-0.0.1.dist-info/top_level.txt
incver-0.0.1.dist-info/RECORD
